{"nodes": [{"id": "c_project_vitograph_apps_web_src_components_dashboard_bottomdock_tsx", "label": "BottomDock.tsx", "file_type": "code", "source_file": "C:\\project\\VITOGRAPH\\apps\\web\\src\\components\\dashboard\\BottomDock.tsx", "source_location": "L1"}, {"id": "dashboard_bottomdock_updatemaskposition", "label": "updateMaskPosition()", "file_type": "code", "source_file": "C:\\project\\VITOGRAPH\\apps\\web\\src\\components\\dashboard\\BottomDock.tsx", "source_location": "L35"}, {"id": "dashboard_bottomdock_handletabclick", "label": "handleTabClick()", "file_type": "code", "source_file": "C:\\project\\VITOGRAPH\\apps\\web\\src\\components\\dashboard\\BottomDock.tsx", "source_location": "L51"}, {"id": "dashboard_bottomdock_handleclosecheckcancel", "label": "handleCloseCheckCancel()", "file_type": "code", "source_file": "C:\\project\\VITOGRAPH\\apps\\web\\src\\components\\dashboard\\BottomDock.tsx", "source_location": "L65"}, {"id": "dashboard_bottomdock_handlecloseprofile", "label": "handleCloseProfile()", "file_type": "code", "source_file": "C:\\project\\VITOGRAPH\\apps\\web\\src\\components\\dashboard\\BottomDock.tsx", "source_location": "L70"}], "edges": [{"source": "c_project_vitograph_apps_web_src_components_dashboard_bottomdock_tsx", "target": "react", "relation": "imports_from", "confidence": "EXTRACTED", "source_file": "C:\\project\\VITOGRAPH\\apps\\web\\src\\components\\dashboard\\BottomDock.tsx", "source_location": "L3", "weight": 1.0}, {"source": "c_project_vitograph_apps_web_src_components_dashboard_bottomdock_tsx", "target": "lucide_react", "relation": "imports_from", "confidence": "EXTRACTED", "source_file": "C:\\project\\VITOGRAPH\\apps\\web\\src\\components\\dashboard\\BottomDock.tsx", "source_location": "L4", "weight": 1.0}, {"source": "c_project_vitograph_apps_web_src_components_dashboard_bottomdock_tsx", "target": "c_project_vitograph_apps_web_src_components_profile_userprofilesheet", "relation": "imports_from", "confidence": "EXTRACTED", "source_file": "C:\\project\\VITOGRAPH\\apps\\web\\src\\components\\dashboard\\BottomDock.tsx", "source_location": "L5", "weight": 1.0}, {"source": "c_project_vitograph_apps_web_src_components_dashboard_bottomdock_tsx", "target": "dashboard_bottomdock_updatemaskposition", "relation": "contains", "confidence": "EXTRACTED", "source_file": "C:\\project\\VITOGRAPH\\apps\\web\\src\\components\\dashboard\\BottomDock.tsx", "source_location": "L35", "weight": 1.0}, {"source": "c_project_vitograph_apps_web_src_components_dashboard_bottomdock_tsx", "target": "dashboard_bottomdock_handletabclick", "relation": "contains", "confidence": "EXTRACTED", "source_file": "C:\\project\\VITOGRAPH\\apps\\web\\src\\components\\dashboard\\BottomDock.tsx", "source_location": "L51", "weight": 1.0}, {"source": "c_project_vitograph_apps_web_src_components_dashboard_bottomdock_tsx", "target": "dashboard_bottomdock_handleclosecheckcancel", "relation": "contains", "confidence": "EXTRACTED", "source_file": "C:\\project\\VITOGRAPH\\apps\\web\\src\\components\\dashboard\\BottomDock.tsx", "source_location": "L65", "weight": 1.0}, {"source": "c_project_vitograph_apps_web_src_components_dashboard_bottomdock_tsx", "target": "dashboard_bottomdock_handlecloseprofile", "relation": "contains", "confidence": "EXTRACTED", "source_file": "C:\\project\\VITOGRAPH\\apps\\web\\src\\components\\dashboard\\BottomDock.tsx", "source_location": "L70", "weight": 1.0}], "raw_calls": [{"caller_nid": "dashboard_bottomdock_updatemaskposition", "callee": "setActiveMaskX", "is_member_call": false, "source_file": "C:\\project\\VITOGRAPH\\apps\\web\\src\\components\\dashboard\\BottomDock.tsx", "source_location": "L40"}, {"caller_nid": "dashboard_bottomdock_handletabclick", "callee": "onTabChange", "is_member_call": false, "source_file": "C:\\project\\VITOGRAPH\\apps\\web\\src\\components\\dashboard\\BottomDock.tsx", "source_location": "L53"}, {"caller_nid": "dashboard_bottomdock_handletabclick", "callee": "setPendingTab", "is_member_call": false, "source_file": "C:\\project\\VITOGRAPH\\apps\\web\\src\\components\\dashboard\\BottomDock.tsx", "source_location": "L56"}, {"caller_nid": "dashboard_bottomdock_handletabclick", "callee": "setTriggerCloseCheck", "is_member_call": false, "source_file": "C:\\project\\VITOGRAPH\\apps\\web\\src\\components\\dashboard\\BottomDock.tsx", "source_location": "L57"}, {"caller_nid": "dashboard_bottomdock_handletabclick", "callee": "onTabChange", "is_member_call": false, "source_file": "C:\\project\\VITOGRAPH\\apps\\web\\src\\components\\dashboard\\BottomDock.tsx", "source_location": "L59"}, {"caller_nid": "dashboard_bottomdock_handletabclick", "callee": "setIsProfileOpen", "is_member_call": false, "source_file": "C:\\project\\VITOGRAPH\\apps\\web\\src\\components\\dashboard\\BottomDock.tsx", "source_location": "L60"}, {"caller_nid": "dashboard_bottomdock_handleclosecheckcancel", "callee": "setTriggerCloseCheck", "is_member_call": false, "source_file": "C:\\project\\VITOGRAPH\\apps\\web\\src\\components\\dashboard\\BottomDock.tsx", "source_location": "L66"}, {"caller_nid": "dashboard_bottomdock_handleclosecheckcancel", "callee": "setPendingTab", "is_member_call": false, "source_file": "C:\\project\\VITOGRAPH\\apps\\web\\src\\components\\dashboard\\BottomDock.tsx", "source_location": "L67"}, {"caller_nid": "dashboard_bottomdock_handlecloseprofile", "callee": "setIsProfileOpen", "is_member_call": false, "source_file": "C:\\project\\VITOGRAPH\\apps\\web\\src\\components\\dashboard\\BottomDock.tsx", "source_location": "L71"}, {"caller_nid": "dashboard_bottomdock_handlecloseprofile", "callee": "setTriggerCloseCheck", "is_member_call": false, "source_file": "C:\\project\\VITOGRAPH\\apps\\web\\src\\components\\dashboard\\BottomDock.tsx", "source_location": "L72"}, {"caller_nid": "dashboard_bottomdock_handlecloseprofile", "callee": "onTabChange", "is_member_call": false, "source_file": "C:\\project\\VITOGRAPH\\apps\\web\\src\\components\\dashboard\\BottomDock.tsx", "source_location": "L74"}, {"caller_nid": "dashboard_bottomdock_handlecloseprofile", "callee": "setPendingTab", "is_member_call": false, "source_file": "C:\\project\\VITOGRAPH\\apps\\web\\src\\components\\dashboard\\BottomDock.tsx", "source_location": "L75"}, {"caller_nid": "dashboard_bottomdock_handlecloseprofile", "callee": "onTabChange", "is_member_call": false, "source_file": "C:\\project\\VITOGRAPH\\apps\\web\\src\\components\\dashboard\\BottomDock.tsx", "source_location": "L77"}]}